sync_version/__init__.py
sync_version/__main__.py
sync_version/loglevel.py
sync_version/sync_version.py
sync_version-0.1.4.dist-info/entry_points.txt
sync_version-0.1.4.dist-info/LICENSE
sync_version-0.1.4.dist-info/WHEEL
sync_version-0.1.4.dist-info/METADATA
sync_version-0.1.4.dist-info/RECORD
