Metadata-Version: 2.1
Name: sync-version
Version: 0.1.4
Summary: Sync __version__ in __init__.py with version in pyproject.toml
Home-page: https://github.com/ffreemt/sync-version
License: MIT
Author: ffreemt
Requires-Python: >=3.8.3,<4.0.0
Classifier: License :: OSI Approved :: MIT License
Classifier: Programming Language :: Python :: 3
Classifier: Programming Language :: Python :: 3.10
Classifier: Programming Language :: Python :: 3.9
Requires-Dist: environs (>=9.5.0,<10.0.0)
Requires-Dist: icecream (>=2.1.1,<3.0.0)
Requires-Dist: install (>=1.3.5,<2.0.0)
Requires-Dist: logzero (>=1.7.0,<2.0.0)
Requires-Dist: tomlkit (>=0.10.1,<0.11.0)
Requires-Dist: typer (>=0.4.1,<0.5.0)
Project-URL: Repository, https://github.com/ffreemt/sync-version
